dukaan
