Metadata-Version: 1.0
Name: dukaan
Version: 0.1.7
Summary: Local testing tool for Windows Azure Store resource providers
Home-page: https://github.com/WindowsAzure/azure-resource-provider-sdk/tree/master/tools/dukaan
Author: UNKNOWN
Author-email: UNKNOWN
License: LICENSE.txt
Platform: UNKNOWN
Classifier: Intended Audience :: Developers
Classifier: Natural Language :: English
Classifier: Programming Language :: Python
Classifier: Programming Language :: Python :: 2.7
